sol_orm_lib/__init__.py
sol_orm_lib/models.py
sol_orm_lib/sol_local_orm.py
sol_orm_lib/sol_orm.py
sol_orm_lib-0.4.8.dist-info/METADATA
sol_orm_lib-0.4.8.dist-info/WHEEL
sol_orm_lib-0.4.8.dist-info/RECORD
