Metadata-Version: 2.1
Name: sol-orm-lib
Version: 0.4.8
Summary: 
Home-page: https://github.com/idener/SOL-Python-ORM-Library
Author: Antonio Gomez
Author-email: antonio.gomez@idener.es
Requires-Python: >=3.8,<4.0
Classifier: Programming Language :: Python :: 3
Classifier: Programming Language :: Python :: 3.8
Classifier: Programming Language :: Python :: 3.9
Classifier: Programming Language :: Python :: 3.10
Classifier: Programming Language :: Python :: 3.11
Classifier: Programming Language :: Python :: 3.12
Requires-Dist: loguru (>=0.7.0,<0.8.0)
Requires-Dist: mysql-connector-python (>=8.2.0,<9.0.0)
Requires-Dist: pydantic (>=1.10.9,<2)
Requires-Dist: requests (>=2.31.0,<3.0.0)
Project-URL: Repository, https://github.com/idener/SOL-Python-ORM-Library
